chatbot_flow/__init__.py
chatbot_flow/core.py
chatbot_flow/exceptions.py
chatbot_flow/flow_manager.py
chatbot_flow/response_generator.py
chatbot_flow/utils.py
chatbot_flow-0.1.0.dist-info/METADATA
chatbot_flow-0.1.0.dist-info/WHEEL
chatbot_flow-0.1.0.dist-info/top_level.txt
chatbot_flow-0.1.0.dist-info/RECORD
